{"name":"19 Trofeo Città di Verolanuova","meetingURL":"https://www.federnuoto.it/home/master/circuito-supermaster/eventi-circuito-supermaster.html#/risultati/136714:19-trofeo-citt%C3%A0-di-verolanuova.html","manifestURL":"/component/solrconnect/download.html?file=L3Zhci93d3cvZmluX2ZpbGVzL2V2ZW50aS8wMDAwMTM2NzE0LnBkZg==","dateDay1":"26","dateMonth1":"Ottobre","dateYear1":"2019","dateDay2":"27","dateMonth2":"Ottobre","dateYear2":"2019","organization":"A.S.D. VEROLANUOTO","venue1":"PISCINA COMUNALE VEROLANUOVA","address1":"VIALE ITALIA, 9 - Verolanuova (BS)","venue2":"","address2":"","poolLength":"25","timeLimit":"SI","registration":"07/10 - 22/10 22:00","sections":[]}