{"name":"Campionati Regionali Master Calabria","meetingURL":"https://www.federnuoto.it/home/master/circuito-supermaster/eventi-circuito-supermaster.html#/risultati/134942:campionati-regionali-master-calabria.html","manifestURL":"/component/solrconnect/download.html?file=L3Zhci93d3cvZmluX2ZpbGVzL2V2ZW50aS8wMDAwMTM0OTQyLnBkZg==","dateDay1":"17","dateMonth1":"Febbraio","dateYear1":"2019","dateDay2":"17","dateMonth2":"Febbraio","dateYear2":"2019","organization":"COMITATO REGIONALE CALABRIA","venue1":"PISCINA COMUNALE COSENZA","address1":"VIA VETERANI DELLO SPORT , SNC - Cosenza (CS)","venue2":"","address2":"","poolLength":"25","timeLimit":"SI","registration":"02/01 - 13/02 10:30","sections":[{"title":"50 Stile Libero - M25","rows":[{"pos":"1","name":"Garritano Domenico","year":"1994","team":"Cosenza Nuoto asd","timing":"26.64","score":"834,83"},{"pos":"2","name":"Cerzoso Gaspare","year":"1994","team":"asd Anzianotti Nuoto","timing":"27.55","score":"807,26"},{"pos":"3","name":"PIRROTTA PASQUALE","year":"1994","team":"Nettuno Nuoto asd - Palmi","timing":"28.04","score":"793,15"},{"pos":"4","name":"CANINO MICHELE","year":"1990","team":"Acli Arvalia Nuoto Lamezi","timing":"29.10","score":"764,26"},{"pos":"5","name":"FERRAGINA GIACOMO","year":"1991","team":"Gruppo Atletico Sportivo","timing":"30.10","score":"738,87"},{"pos":"6","name":"BOSA NICOLA","year":"1992","team":"asd Anzianotti Nuoto","timing":"30.36","score":"732,54"},{"pos":"7","name":"PORCO STEFANO","year":"1991","team":"asd Anzianotti Nuoto","timing":"32.66","score":"680,96"},{"pos":"8","name":"Rendace Piero","year":"1990","team":"asd Anzianotti Nuoto","timing":"32.88","score":"676,40"},{"pos":"9","name":"SEVERINO MATTEO","year":"1992","team":"Gruppo Atletico Sportivo","timing":"33.46","score":"664,67"},{"pos":"10","name":"D'AGOSTINO DANIEL","year":"1992","team":"asd Anzianotti Nuoto","timing":"35.23","score":"631,28"}]},{"title":"50 Stile Libero - M30","rows":[{"pos":"1","name":"MIRANTE SERGIO","year":"1989","team":"Gruppo Atletico Sportivo","timing":"25.53","score":"872,31"},{"pos":"2","name":"MAZZUCA GIOVANNI","year":"1989","team":"asd Anzianotti Nuoto","timing":"26.74","score":"832,83"},{"pos":"3","name":"Masala Antonello","year":"1987","team":"Acli Arvalia Nuoto Lamezi","timing":"27.44","score":"811,59"},{"pos":"4","name":"Strangis Francesco","year":"1986","team":"Acli Arvalia Nuoto Lamezi","timing":"29.71","score":"749,58"},{"pos":"5","name":"Bartucci Stefano","year":"1985","team":"asd Anzianotti Nuoto","timing":"30.32","score":"734,50"},{"pos":"6","name":"PAGLIARO GIUSEPPE","year":"1989","team":"asd Anzianotti Nuoto","timing":"32.58","score":"683,55"},{"pos":"7","name":"FERRARO GABRIELE","year":"1989","team":"Calabria Swim Race asd","timing":"32.75","score":"680,00"},{"pos":"8","name":"SAFFIOTI FILIPPO","year":"1985","team":"Nettuno Nuoto asd - Palmi","timing":"34.40","score":"647,38"},{"pos":"9","name":"Garcea Nicola","year":"1985","team":"Calabria Swim Race asd","timing":"34.81","score":"639,76"},{"pos":"10","name":"Manna Ernesto","year":"1986","team":"Cosenza Nuoto asd","timing":"35.10","score":"634,47"},{"pos":"11","name":"SCORNAIENGHI FRANCESCO","year":"1986","team":"asd Anzianotti Nuoto","timing":"35.19","score":"632,85"}]},{"title":"50 Stile Libero - M35","rows":[{"pos":"1","name":"ATZENI PAOLO","year":"1982","team":"Calabria Swim Race asd","timing":"26.96","score":"845,33"},{"pos":"2","name":"BERLINGIERI DIEGO","year":"1984","team":"CN Sub Villa S.Giovanni","timing":"28.73","score":"793,25"},{"pos":"3","name":"CUNZOLO GIUSEPPE","year":"1983","team":"Nettuno Nuoto asd - Palmi","timing":"31.70","score":"718,93"},{"pos":"4","name":"D' Alessandro Antonio","year":"1982","team":"Sport4life ssd","timing":"32.92","score":"692,28"},{"pos":"5","name":"TENUTA MATTIA","year":"1984","team":"Sport4life ssd","timing":"33.19","score":"686,65"},{"pos":"6","name":"Aiello Francesco","year":"1984","team":"Sport4life ssd","timing":"33.70","score":"676,26"},{"pos":"7","name":"MURACA STEFANO","year":"1983","team":"asd Anzianotti Nuoto","timing":"33.79","score":"674,46"},{"pos":"8","name":"Vincelli Pierpaolo","year":"1981","team":"Catanzaro Nuoto asd","timing":"33.93","score":"671,68"},{"pos":"9","name":"NAPOLITANO GIOVANNI","year":"1983","team":"Nettuno Nuoto asd - Palmi","timing":"34.10","score":"668,33"},{"pos":"10","name":"Cosimo Gaetano","year":"1983","team":"Nettuno Nuoto asd - Palmi","timing":"34.26","score":"665,21"},{"pos":"11","name":"NAPOLITANO ANTONIO","year":"1984","team":"asd Anzianotti Nuoto","timing":"34.32","score":"664,04"},{"pos":"12","name":"DENARO FRANCESCO","year":"1981","team":"Calabria Swim Race asd","timing":"34.49","score":"660,77"},{"pos":"13","name":"BEVACQUA ROCCO","year":"1983","team":"CN Sub Villa S.Giovanni","timing":"35.68","score":"638,73"},{"pos":"14","name":"Aiello Domenico","year":"1984","team":"Gruppo Atletico Sportivo","timing":"39.26","score":"580,49"},{"pos":"15","name":"LUCIA ANDREA","year":"1981","team":"Gruppo Atletico Sportivo","timing":"40.37","score":"564,53"}]},{"title":"50 Stile Libero - M40","rows":[{"pos":"1","name":"VRENNA LUCA","year":"1979","team":"Lacinia Nuoto","timing":"28.09","score":"828,41"},{"pos":"2","name":"IANNI' ROCCO","year":"1977","team":"Nettuno Nuoto asd - Palmi","timing":"28.59","score":"813,92"},{"pos":"3","name":"Manna Francesco","year":"1978","team":"Cosenza Nuoto asd","timing":"28.87","score":"806,03"},{"pos":"4","name":"MONTIMURRO MASSIMO","year":"1976","team":"asd Anzianotti Nuoto","timing":"29.39","score":"791,77"},{"pos":"5","name":"Celso Agatino","year":"1975","team":"Cosenza Nuoto asd","timing":"29.49","score":"789,08"},{"pos":"6","name":"VONA GIUSEPPE","year":"1975","team":"HdueO Sport & Animaz. CT","timing":"30.03","score":"774,89"},{"pos":"7","name":"BORELLO PIETRO","year":"1975","team":"Acli Arvalia Nuoto Lamezi","timing":"30.20","score":"770,53"},{"pos":"8","name":"Lorenzano Antonio","year":"1979","team":"Lacinia Nuoto","timing":"30.88","score":"753,56"},{"pos":"9","name":"Imbrogno Natalino","year":"1977","team":"asd Anzianotti Nuoto","timing":"30.96","score":"751,61"},{"pos":"10","name":"Favretto Ivan","year":"1978","team":"Sport4life ssd","timing":"34.04","score":"683,61"},{"pos":"11","name":"BELCASTRO GIOVANNI","year":"1979","team":"Cosenza Nuoto asd","timing":"34.19","score":"680,61"},{"pos":"12","name":"CORTESE SALVATORE","year":"1977","team":"Acli Arvalia Nuoto Lamezi","timing":"34.87","score":"667,34"},{"pos":"13","name":"Baratta Luca","year":"1975","team":"Sport4life ssd","timing":"35.27","score":"659,77"},{"pos":"14","name":"LEONARDO DANILO","year":"1976","team":"Calabria Swim Race asd","timing":"35.43","score":"656,79"},{"pos":"15","name":"SIGNORETTA MASSIMO","year":"1978","team":"Cosenza Nuoto asd","timing":"36.60","score":"635,79"},{"pos":"16","name":"COSENTINO SALVATORE","year":"1977","team":"Catanzaro Nuoto asd","timing":"37.70","score":"617,24"},{"pos":"17","name":"FEZZA GIUSEPPE","year":"1975","team":"asd Anzianotti Nuoto","timing":"37.92","score":"613,66"},{"pos":"18","name":"Bucarelli Luigi","year":"1977","team":"Cosenza Nuoto asd","timing":"39.53","score":"588,67"},{"pos":"19","name":"Puntillo Salvatore","year":"1977","team":"asd Anzianotti Nuoto","timing":"39.72","score":"585,85"},{"pos":"20","name":"Cerminara Domenico","year":"1975","team":"Acli Arvalia Nuoto Lamezi","timing":"41.07","score":"566,59"},{"pos":"21","name":"Giordano Alessandro","year":"1976","team":"Sport4life ssd","timing":"44.97","score":"517,46"},{"pos":"22","name":"Gradilone Raffaele","year":"1977","team":"asd Anzianotti Nuoto","timing":"46.33","score":"502,27"},{"pos":"23","name":"Consolo Luca","year":"1976","team":"Cosenza Nuoto asd","timing":"46.84","score":"496,80"}]},{"title":"50 Stile Libero - M45","rows":[{"pos":"1","name":"ALAMPI PIERFRANCESCO","year":"1971","team":"Lacinia Nuoto","timing":"27.44","score":"864,80"},{"pos":"2","name":"ROCCA SALVATORE","year":"1973","team":"HdueO Sport & Animaz. CT","timing":"27.86","score":"851,76"},{"pos":"3","name":"FILIPPELLI PAOLO","year":"1973","team":"Lacinia Nuoto","timing":"30.82","score":"769,95"},{"pos":"4","name":"GRISAFI PIERGIORGIO","year":"1972","team":"Lacinia Nuoto","timing":"32.56","score":"728,81"},{"pos":"5","name":"PRETE CRISTIAN","year":"1971","team":"asd Anzianotti Nuoto","timing":"32.80","score":"723,48"},{"pos":"6","name":"VIOLA GIANLUCA","year":"1973","team":"Lacinia Nuoto","timing":"33.59","score":"706,46"},{"pos":"7","name":"TORCASIO GIUSEPPE","year":"1971","team":"Acli Arvalia Nuoto Lamezi","timing":"33.70","score":"704,15"},{"pos":"8","name":"De Marco Fernando","year":"1970","team":"Sport4life ssd","timing":"34.24","score":"693,05"},{"pos":"9","name":"RHODIO FRANCESCO","year":"1973","team":"Catanzaro Nuoto asd","timing":"34.33","score":"691,23"},{"pos":"10","name":"COMIS GIUSEPPE","year":"1971","team":"Gruppo Atletico Sportivo","timing":"34.37","score":"690,43"},{"pos":"11","name":"VAZZANA FABIO","year":"1973","team":"CN Sub Villa S.Giovanni","timing":"34.60","score":"685,84"},{"pos":"12","name":"GULINO ROBERTO","year":"1973","team":"asd Anzianotti Nuoto","timing":"34.63","score":"685,24"},{"pos":"13","name":"PIROZZI ERMINIO","year":"1973","team":"asd Anzianotti Nuoto","timing":"34.67","score":"684,45"},{"pos":"14","name":"RUSSO ALESSANDRO","year":"1971","team":"Sport4life ssd","timing":"35.08","score":"676,45"},{"pos":"15","name":"FIORENZA ILARIO MASSIMO","year":"1972","team":"Calabria Swim Race asd","timing":"35.45","score":"669,39"},{"pos":"16","name":"FIORITO GIUSEPPE","year":"1970","team":"Gruppo Atletico Sportivo","timing":"35.96","score":"659,90"},{"pos":"17","name":"Carillio Guido","year":"1974","team":"Catanzaro Nuoto asd","timing":"36.32","score":"653,36"},{"pos":"18","name":"Spada Carlo","year":"1970","team":"Catanzaro Nuoto asd","timing":"37.41","score":"634,32"},{"pos":"19","name":"Cerchiaro Giuseppe","year":"1974","team":"Sport4life ssd","timing":"39.47","score":"601,22"},{"pos":"20","name":"Romanello Giuseppe","year":"1972","team":"Catanzaro Nuoto asd","timing":"41.95","score":"565,67"},{"pos":"21","name":"Zappala Raffaele","year":"1973","team":"Lacinia Nuoto","timing":"41.99","score":"565,13"},{"pos":"22","name":"BRUNI PIERLUCA","year":"1970","team":"Sport4life ssd","timing":"43.34","score":"547,53"},{"pos":"23","name":"CAPUANO RUGGERO","year":"1973","team":"Lacinia Nuoto","timing":"43.82","score":"541,53"},{"pos":"24","name":"Scalzo Enrico Salvatore","year":"1972","team":"asd Anzianotti Nuoto","timing":"48.44","score":"489,88"},{"pos":"25","name":"TORCASIO VINCENZO","year":"1971","team":"Acli Arvalia Nuoto Lamezi","timing":"49.33","score":"481,05"}]},{"title":"50 Stile Libero - M50","rows":[{"pos":"1","name":"ARMINI ALFONSO","year":"1969","team":"asd Anzianotti Nuoto","timing":"29.78","score":"824,38"},{"pos":"2","name":"SARACO CLAUDIO","year":"1967","team":"Lacinia Nuoto","timing":"33.50","score":"732,84"},{"pos":"3","name":"TURTORO POMPILIO","year":"1969","team":"Acli Arvalia Nuoto Lamezi","timing":"35.78","score":"686,14"},{"pos":"4","name":"SARRA FABIO MARIA","year":"1967","team":"CN Sub Villa S.Giovanni","timing":"35.78","score":"686,14"},{"pos":"5","name":"MOLINARI LORENZO","year":"1969","team":"CS Il Gabbiano Paola ssd","timing":"36.45","score":"673,53"},{"pos":"6","name":"DI DONNA ANDREA","year":"1967","team":"Cosenza Nuoto asd","timing":"36.52","score":"672,23"},{"pos":"7","name":"GARGANO GIANCARLO","year":"1966","team":"asd Anzianotti Nuoto","timing":"37.43","score":"655,89"},{"pos":"8","name":"RIOLO MARIO","year":"1966","team":"Lacinia Nuoto","timing":"38.75","score":"633,55"},{"pos":"9","name":"CAPANO GIUSEPPE","year":"1965","team":"CS Il Gabbiano Paola ssd","timing":"38.76","score":"633,38"},{"pos":"10","name":"Rosa Rocco","year":"1969","team":"Sport4life ssd","timing":"39.17","score":"626,76"},{"pos":"11","name":"TALARICO FRANCESCO","year":"1966","team":"Catanzaro Nuoto asd","timing":"40.08","score":"612,52"},{"pos":"12","name":"NOTTI ETTORE","year":"1966","team":"Sport4life ssd","timing":"45.26","score":"542,42"}]},{"title":"50 Stile Libero - M55","rows":[{"pos":"1","name":"AMIDEO FELICE","year":"1962","team":"Lacinia Nuoto","timing":"29.63","score":"847,45"},{"pos":"2","name":"MILIZIA FABIO","year":"1964","team":"Lacinia Nuoto","timing":"31.20","score":"804,81"},{"pos":"3","name":"VARZI VINCENZO","year":"1963","team":"Gruppo Atletico Sportivo","timing":"31.31","score":"801,98"},{"pos":"4","name":"LATTARI MASSIMO","year":"1963","team":"CS Il Gabbiano Paola ssd","timing":"31.81","score":"789,37"},{"pos":"5","name":"Valentino Pierpaolo","year":"1964","team":"Acli Arvalia Nuoto Lamezi","timing":"35.56","score":"706,13"},{"pos":"6","name":"MESSINA NICOLA ANTONIO","year":"1960","team":"Lacinia Nuoto","timing":"36.31","score":"691,55"},{"pos":"7","name":"LIBRI DEMETRIO","year":"1962","team":"CN Sub Villa S.Giovanni","timing":"37.86","score":"663,23"},{"pos":"8","name":"Mastrangelo Giuseppe","year":"1963","team":"Sport4life ssd","timing":"38.98","score":"644,18"},{"pos":"9","name":"Verduci Antonino","year":"1964","team":"Cosenza Nuoto asd","timing":"39.31","score":"638,77"},{"pos":"10","name":"Manfredi Riccardo","year":"1964","team":"Sport4life ssd","timing":"41.53","score":"604,62"},{"pos":"11","name":"CAPUTO ANTONIO","year":"1962","team":"Sport4life ssd","timing":"44.61","score":"562,88"}]},{"title":"50 Stile Libero - M60","rows":[{"pos":"1","name":"MAZZUCA NICOLA","year":"1956","team":"Catanzaro Nuoto asd","timing":"35.12","score":"737,47"},{"pos":"2","name":"GIAMPA' FRANCESCO","year":"1957","team":"Calabria Swim Race asd","timing":"35.52","score":"729,17"},{"pos":"3","name":"GENTILE MARIO","year":"1959","team":"Sport4life ssd","timing":"36.88","score":"702,28"},{"pos":"4","name":"MORABITO GIUSEPPE","year":"1956","team":"CN Sub Villa S.Giovanni","timing":"37.88","score":"683,74"},{"pos":"5","name":"PECORA BRUNO","year":"1959","team":"CN Sub Villa S.Giovanni","timing":"40.67","score":"636,83"},{"pos":"6","name":"SQUILLACE FRANCESCO","year":"1956","team":"Catanzaro Nuoto asd","timing":"43.88","score":"590,25"},{"pos":"7","name":"Aloi Giuseppe","year":"1958","team":"Sport4life ssd","timing":"44.51","score":"581,89"},{"pos":"8","name":"POSTERINO DOMENICO","year":"1958","team":"Nettuno Nuoto asd - Palmi","timing":"45.82","score":"565,26"}]},{"title":"100 Stile Libero - M25","rows":[{"pos":"1","name":"BOSA NICOLA","year":"1992","team":"asd Anzianotti Nuoto","timing":"01:12.73","score":"677,85"},{"pos":"2","name":"Preiti Francesco","year":"1993","team":"Cosenza Nuoto asd","timing":"01:15.67","score":"651,51"},{"pos":"3","name":"PORCO STEFANO","year":"1991","team":"asd Anzianotti Nuoto","timing":"01:20.57","score":"611,89"},{"pos":"4","name":"D'AGOSTINO DANIEL","year":"1992","team":"asd Anzianotti Nuoto","timing":"01:22.33","score":"598,81"}]},{"title":"100 Stile Libero - M30","rows":[{"pos":"1","name":"MIRANTE SERGIO","year":"1989","team":"Gruppo Atletico Sportivo","timing":"56.79","score":"869,70"},{"pos":"2","name":"Caracciolo Aldo","year":"1989","team":"Calabria Swim Race asd","timing":"01:14.45","score":"663,40"},{"pos":"3","name":"TYMPANI ALESSIO","year":"1987","team":"Catanzaro Nuoto asd","timing":"01:15.93","score":"650,47"},{"pos":"4","name":"SCORNAIENGHI FRANCESCO","year":"1986","team":"asd Anzianotti Nuoto","timing":"01:20.47","score":"613,77"},{"pos":"5","name":"Mascaro Vincenzo","year":"1989","team":"Acli Arvalia Nuoto Lamezi","timing":"01:36.26","score":"513,09"}]},{"title":"100 Stile Libero - M35","rows":[{"pos":"1","name":"PREZIOSI GIANLUCA","year":"1981","team":"Jolly Nuoto Cl. Benevento","timing":"01:03.88","score":"796,02"},{"pos":"2","name":"ALLORI MARCO","year":"1981","team":"asd Anzianotti Nuoto","timing":"01:04.18","score":"792,30"},{"pos":"3","name":"CORAPI ANTONIO","year":"1980","team":"Calabria Swim Race asd","timing":"01:05.49","score":"776,45"},{"pos":"4","name":"CIPOLLA GAETANO","year":"1981","team":"Wellnext ssd arl","timing":"01:13.09","score":"695,72"},{"pos":"5","name":"BEVACQUA ROCCO","year":"1983","team":"CN Sub Villa S.Giovanni","timing":"01:15.91","score":"669,87"},{"pos":"6","name":"D'ALESSIO ALFONSO","year":"1981","team":"Calabria Swim Race asd","timing":"01:31.99","score":"552,78"}]},{"title":"100 Stile Libero - M40","rows":[{"pos":"1","name":"COSTA GIOVANNI","year":"1976","team":"asd Anzianotti Nuoto","timing":"01:07.93","score":"755,19"},{"pos":"2","name":"Alitto Gabriele","year":"1978","team":"Sport4life ssd","timing":"01:27.23","score":"588,10"},{"pos":"3","name":"Puntillo Salvatore","year":"1977","team":"asd Anzianotti Nuoto","timing":"01:34.49","score":"542,91"},{"pos":"4","name":"Gradilone Raffaele","year":"1977","team":"asd Anzianotti Nuoto","timing":"01:54.55","score":"447,84"}]},{"title":"100 Stile Libero - M45","rows":[{"pos":"1","name":"ALAMPI PIERFRANCESCO","year":"1971","team":"Lacinia Nuoto","timing":"01:01.19","score":"862,23"},{"pos":"2","name":"ROCCA SALVATORE","year":"1973","team":"HdueO Sport & Animaz. CT","timing":"01:04.65","score":"816,09"},{"pos":"3","name":"Alfano Salvatore","year":"1970","team":"Sport4life ssd","timing":"01:15.43","score":"699,46"},{"pos":"4","name":"Rizzuti Antonio","year":"1971","team":"Catanzaro Nuoto asd","timing":"01:23.49","score":"631,93"},{"pos":"5","name":"BRUNI PIERLUCA","year":"1970","team":"Sport4life ssd","timing":"01:36.76","score":"545,27"},{"pos":"6","name":"Romanello Giuseppe","year":"1972","team":"Catanzaro Nuoto asd","timing":"01:51.17","score":"474,59"}]},{"title":"100 Stile Libero - M50","rows":[{"pos":"1","name":"ZACCONE ANDREA","year":"1969","team":"Catanzaro Nuoto asd","timing":"01:13.92","score":"737,69"},{"pos":"2","name":"SARRA FABIO MARIA","year":"1967","team":"CN Sub Villa S.Giovanni","timing":"01:13.98","score":"737,09"},{"pos":"3","name":"LAGANA' DEMETRIO","year":"1968","team":"asd Anzianotti Nuoto","timing":"01:18.02","score":"698,92"},{"pos":"4","name":"MOLINARI LORENZO","year":"1969","team":"CS Il Gabbiano Paola ssd","timing":"01:28.92","score":"613,25"}]},{"title":"100 Stile Libero - M55","rows":[{"pos":"1","name":"LATTARI MASSIMO","year":"1963","team":"CS Il Gabbiano Paola ssd","timing":"01:11.95","score":"782,63"},{"pos":"2","name":"CACCURI BAFFA ROSARIO","year":"1961","team":"asd Anzianotti Nuoto","timing":"01:13.18","score":"769,47"},{"pos":"3","name":"Sapia Domenico","year":"1962","team":"asd Anzianotti Nuoto","timing":"01:28.51","score":"636,20"}]},{"title":"100 Stile Libero - M60","rows":[{"pos":"1","name":"MAZZUCA NICOLA","year":"1956","team":"Catanzaro Nuoto asd","timing":"01:24.01","score":"690,75"}]},{"title":"100 Stile Libero - M65","rows":[{"pos":"1","name":"GUIDUCCI MAURIZIO","year":"1953","team":"Catanzaro Nuoto asd","timing":"01:51.91","score":"538,56"}]},{"title":"200 Stile Libero - M30","rows":[{"pos":"1","name":"BONOMO SIGISMONDO","year":"1989","team":"Olympiapalermo asd","timing":"02:07.53","score":"857,99"},{"pos":"2","name":"TYMPANI ALESSIO","year":"1987","team":"Catanzaro Nuoto asd","timing":"03:00.04","score":"607,75"},{"pos":"3","name":"Mascaro Vincenzo","year":"1989","team":"Acli Arvalia Nuoto Lamezi","timing":"03:38.84","score":"500,00"}]},{"title":"200 Stile Libero - M35","rows":[{"pos":"1","name":"SORRENTINO PIETRO ANTONIO","year":"1981","team":"Sky Sporting ssd","timing":"02:36.07","score":"725,06"},{"pos":"2","name":"D' Alessandro Antonio","year":"1982","team":"Sport4life ssd","timing":"03:04.80","score":"612,34"}]},{"title":"200 Stile Libero - M40","rows":[{"pos":"1","name":"CATONA SIMONE","year":"1978","team":"CN Sub Villa S.Giovanni","timing":"02:22.11","score":"807,75"},{"pos":"2","name":"CARIDA' FRANCESCO","year":"1976","team":"Calabria Swim Race asd","timing":"02:36.17","score":"735,03"},{"pos":"3","name":"COSTA GIOVANNI","year":"1976","team":"asd Anzianotti Nuoto","timing":"02:36.24","score":"734,70"},{"pos":"4","name":"RUFFOLO EUGENIO","year":"1976","team":"asd Anzianotti Nuoto","timing":"02:52.07","score":"667,11"},{"pos":"5","name":"GIGLIO FILIPPO","year":"1976","team":"asd Anzianotti Nuoto","timing":"02:53.08","score":"663,22"},{"pos":"6","name":"MACRI' EMANUELE","year":"1978","team":"asd Anzianotti Nuoto","timing":"02:55.98","score":"652,29"},{"pos":"7","name":"FEZZA GIUSEPPE","year":"1975","team":"asd Anzianotti Nuoto","timing":"03:34.34","score":"535,55"}]},{"title":"200 Stile Libero - M45","rows":[{"pos":"1","name":"Fodero Leonardo","year":"1974","team":"Catanzaro Nuoto asd","timing":"02:21.79","score":"820,65"},{"pos":"2","name":"PIROZZI ERMINIO","year":"1973","team":"asd Anzianotti Nuoto","timing":"02:56.29","score":"660,05"}]},{"title":"200 Stile Libero - M50","rows":[{"pos":"1","name":"ARMINI ALFONSO","year":"1969","team":"asd Anzianotti Nuoto","timing":"02:34.88","score":"775,44"},{"pos":"2","name":"ZACCONE ANDREA","year":"1969","team":"Catanzaro Nuoto asd","timing":"02:57.43","score":"676,89"},{"pos":"3","name":"ARBITRIO CARLO","year":"1966","team":"CN Sub Villa S.Giovanni","timing":"03:03.38","score":"654,92"},{"pos":"4","name":"ARTUSO MASSIMILIANO","year":"1967","team":"asd Anzianotti Nuoto","timing":"03:21.65","score":"595,59"},{"pos":"5","name":"GUZZO ANTONIO","year":"1966","team":"Acli Arvalia Nuoto Lamezi","timing":"03:33.57","score":"562,34"}]},{"title":"200 Stile Libero - M60","rows":[{"pos":"1","name":"TRECROCI ALDO","year":"1957","team":"asd Anzianotti Nuoto","timing":"03:04.78","score":"702,57"},{"pos":"2","name":"ISABELLA CARLO LUIGI","year":"1959","team":"Acli Arvalia Nuoto Lamezi","timing":"03:18.17","score":"655,09"}]},{"title":"400 Stile Libero - M25","rows":[{"pos":"1","name":"PIRROTTA PASQUALE","year":"1994","team":"Nettuno Nuoto asd - Palmi","timing":"04:55.19","score":"804,46"},{"pos":"2","name":"CANINO MICHELE","year":"1990","team":"Acli Arvalia Nuoto Lamezi","timing":"05:31.30","score":"716,78"}]},{"title":"400 Stile Libero - M30","rows":[{"pos":"1","name":"DE MARIA GIOVANNI","year":"1989","team":"asd Anzianotti Nuoto","timing":"05:01.17","score":"799,02"},{"pos":"2","name":"FERRARO GABRIELE","year":"1989","team":"Calabria Swim Race asd","timing":"07:17.92","score":"549,51"}]},{"title":"400 Stile Libero - M35","rows":[{"pos":"1","name":"CORAPI ANTONIO","year":"1980","team":"Calabria Swim Race asd","timing":"05:05.97","score":"791,52"},{"pos":"2","name":"NAPOLITANO GIOVANNI","year":"1983","team":"Nettuno Nuoto asd - Palmi","timing":"06:13.54","score":"648,34"}]},{"title":"400 Stile Libero - M40","rows":[{"pos":"1","name":"CASTALDO ARCANGELO","year":"1977","team":"Catanzaro Nuoto asd","timing":"05:51.49","score":"693,39"},{"pos":"2","name":"CORTESE SALVATORE","year":"1977","team":"Acli Arvalia Nuoto Lamezi","timing":"06:12.66","score":"654,00"},{"pos":"3","name":"Umbrello Domenico","year":"1976","team":"Sport4life ssd","timing":"06:15.00","score":"649,92"},{"pos":"4","name":"Cerminara Domenico","year":"1975","team":"Acli Arvalia Nuoto Lamezi","timing":"07:20.78","score":"552,93"}]},{"title":"400 Stile Libero - M45","rows":[{"pos":"1","name":"Fodero Leonardo","year":"1974","team":"Catanzaro Nuoto asd","timing":"04:53.61","score":"849,66"},{"pos":"2","name":"ALBISI DOMENICO","year":"1971","team":"Acli Arvalia Nuoto Lamezi","timing":"05:42.46","score":"728,46"},{"pos":"3","name":"BRUNO GIOVANNI","year":"1971","team":"asd Anzianotti Nuoto","timing":"05:54.70","score":"703,33"},{"pos":"4","name":"VAZZANA FABIO","year":"1973","team":"CN Sub Villa S.Giovanni","timing":"05:58.94","score":"695,02"},{"pos":"5","name":"CARBONE LUCA","year":"1973","team":"Sport4life ssd","timing":"05:59.02","score":"694,86"},{"pos":"6","name":"GRECO ANGELO","year":"1973","team":"asd Anzianotti Nuoto","timing":"06:01.70","score":"689,72"},{"pos":"7","name":"RHODIO FRANCESCO","year":"1973","team":"Catanzaro Nuoto asd","timing":"06:30.05","score":"639,58"},{"pos":"8","name":"GULINO ROBERTO","year":"1973","team":"asd Anzianotti Nuoto","timing":"06:33.20","score":"634,46"},{"pos":"9","name":"IUDICA GIUSEPPE","year":"1970","team":"HdueO Sport & Animaz. CT","timing":"06:44.70","score":"616,43"},{"pos":"10","name":"Spada Carlo","year":"1970","team":"Catanzaro Nuoto asd","timing":"06:56.87","score":"598,44"},{"pos":"11","name":"CESARIO VINCENZO","year":"1971","team":"Sport4life ssd","timing":"06:59.43","score":"594,78"},{"pos":"12","name":"Rizzuti Antonio","year":"1971","team":"Catanzaro Nuoto asd","timing":"08:03.55","score":"515,91"},{"pos":"13","name":"Carillio Guido","year":"1974","team":"Catanzaro Nuoto asd","timing":"09:25.80","score":"440,92"}]},{"title":"400 Stile Libero - M50","rows":[{"pos":"1","name":"ARTUSO MASSIMILIANO","year":"1967","team":"asd Anzianotti Nuoto","timing":"06:58.40","score":"616,95"},{"pos":"2","name":"RIOLO MARIO","year":"1966","team":"Lacinia Nuoto","timing":"07:08.83","score":"601,94"},{"pos":"3","name":"Mazzotta Massimo","year":"1966","team":"asd Anzianotti Nuoto","timing":"07:23.27","score":"582,33"}]},{"title":"400 Stile Libero - M55","rows":[{"pos":"1","name":"ZIZZA ANTONIO","year":"1963","team":"Lacinia Nuoto","timing":"06:33.74","score":"687,33"},{"pos":"2","name":"Sapia Domenico","year":"1962","team":"asd Anzianotti Nuoto","timing":"07:23.71","score":"609,93"}]},{"title":"400 Stile Libero - M60","rows":[{"pos":"1","name":"MIRANTE PATRIZIO","year":"1958","team":"asd Anzianotti Nuoto","timing":"06:23.39","score":"731,53"},{"pos":"2","name":"TRECROCI ALDO","year":"1957","team":"asd Anzianotti Nuoto","timing":"06:34.60","score":"710,75"},{"pos":"3","name":"GIAMPA' FRANCESCO","year":"1957","team":"Calabria Swim Race asd","timing":"06:34.76","score":"710,46"},{"pos":"4","name":"SQUILLACE FRANCESCO","year":"1956","team":"Catanzaro Nuoto asd","timing":"08:24.47","score":"555,95"}]},{"title":"400 Stile Libero - M65","rows":[{"pos":"1","name":"CAMERA CAMILLO","year":"1953","team":"Lacinia Nuoto","timing":"06:43.10","score":"734,71"}]},{"title":"400 Stile Libero - M70","rows":[{"pos":"1","name":"GRECO ANSELMO","year":"1949","team":"Lacinia Nuoto","timing":"10:37.75","score":"499,66"}]},{"title":"800 Stile Libero - M30","rows":[{"pos":"1","name":"LA BRUNA ROSARIO","year":"1989","team":"CN Sub Villa S.Giovanni","timing":"10:00.84","score":"839,99"},{"pos":"2","name":"Lamberti Luca","year":"1985","team":"Sport4life ssd","timing":"11:57.08","score":"703,83"}]},{"title":"800 Stile Libero - M40","rows":[{"pos":"1","name":"CARIDA' FRANCESCO","year":"1976","team":"Calabria Swim Race asd","timing":"11:45.70","score":"719,17"},{"pos":"2","name":"Umbrello Domenico","year":"1976","team":"Sport4life ssd","timing":"12:42.09","score":"665,96"},{"pos":"3","name":"GIGLIO FILIPPO","year":"1976","team":"asd Anzianotti Nuoto","timing":"13:38.14","score":"620,33"}]},{"title":"800 Stile Libero - M45","rows":[{"pos":"1","name":"LO SCAVO FRANCESCO","year":"1974","team":"Catanzaro Nuoto asd","timing":"12:20.26","score":"704,87"},{"pos":"2","name":"CARBONE LUCA","year":"1973","team":"Sport4life ssd","timing":"12:21.31","score":"703,88"}]},{"title":"800 Stile Libero - M50","rows":[{"pos":"1","name":"RODIO ANTONIO","year":"1968","team":"Lacinia Nuoto","timing":"10:28.39","score":"861,73"},{"pos":"2","name":"CASERTA VITALIANO","year":"1967","team":"Calabria Swim Race asd","timing":"10:48.78","score":"834,64"},{"pos":"3","name":"CAPRINO PASQUALE","year":"1968","team":"asd Anzianotti Nuoto","timing":"13:26.72","score":"671,24"},{"pos":"4","name":"CIMARRUSTI GIACOMO","year":"1965","team":"Calabria Swim Race asd","timing":"14:02.29","score":"642,89"},{"pos":"5","name":"GUZZO ANTONIO","year":"1966","team":"Acli Arvalia Nuoto Lamezi","timing":"15:26.74","score":"584,31"}]},{"title":"800 Stile Libero - M55","rows":[{"pos":"1","name":"ROTUNDO GIOVANNI","year":"1964","team":"Calabria Swim Race asd","timing":"12:41.57","score":"735,51"},{"pos":"2","name":"CAPILLO STELLARIO","year":"1961","team":"Catanzaro Nuoto asd","timing":"15:48.20","score":"590,74"}]},{"title":"800 Stile Libero - M60","rows":[{"pos":"1","name":"PORCARO ALFREDO","year":"1959","team":"Cosenza Nuoto asd","timing":"12:31.50","score":"782,16"},{"pos":"2","name":"ISABELLA CARLO LUIGI","year":"1959","team":"Acli Arvalia Nuoto Lamezi","timing":"14:22.95","score":"681,14"}]},{"title":"800 Stile Libero - M65","rows":[{"pos":"1","name":"GAROFALO FRANCESCO","year":"1954","team":"Lacinia Nuoto","timing":"11:19.47","score":"908,55"}]},{"title":"1500 Stile Libero - M30","rows":[{"pos":"1","name":"LA BRUNA ROSARIO","year":"1989","team":"CN Sub Villa S.Giovanni","timing":"19:03.29","score":"848,19"}]},{"title":"1500 Stile Libero - M35","rows":[{"pos":"1","name":"CINTORINO ANTONINO","year":"1982","team":"Calabria Swim Race asd","timing":"24:37.61","score":"657,37"}]},{"title":"1500 Stile Libero - M40","rows":[{"pos":"1","name":"RUFFOLO EUGENIO","year":"1976","team":"asd Anzianotti Nuoto","timing":"23:57.09","score":"682,94"}]},{"title":"1500 Stile Libero - M45","rows":[{"pos":"1","name":"ALBISI DOMENICO","year":"1971","team":"Acli Arvalia Nuoto Lamezi","timing":"22:11.19","score":"755,74"}]},{"title":"1500 Stile Libero - M50","rows":[{"pos":"1","name":"CAPRINO PASQUALE","year":"1968","team":"asd Anzianotti Nuoto","timing":"25:44.64","score":"667,39"},{"pos":"2","name":"CIMARRUSTI GIACOMO","year":"1965","team":"Calabria Swim Race asd","timing":"26:29.55","score":"648,53"},{"pos":"3","name":"Mazzotta Massimo","year":"1966","team":"asd Anzianotti Nuoto","timing":"29:09.06","score":"589,39"}]},{"title":"1500 Stile Libero - M60","rows":[{"pos":"1","name":"PORCARO ALFREDO","year":"1959","team":"Cosenza Nuoto asd","timing":"24:06.58","score":"782,63"},{"pos":"2","name":"CROCEROSSA MARCELLO","year":"1958","team":"asd Anzianotti Nuoto","timing":"29:13.15","score":"645,77"}]},{"title":"1500 Stile Libero - M65","rows":[{"pos":"1","name":"CAMERA CAMILLO","year":"1953","team":"Lacinia Nuoto","timing":"25:29.18","score":"773,24"}]},{"title":"1500 Stile Libero - M70","rows":[{"pos":"1","name":"GRECO ANSELMO","year":"1949","team":"Lacinia Nuoto","timing":"41:04.35","score":"528,07"}]},{"title":"50 Dorso - M25","rows":[{"pos":"1","name":"Garritano Domenico","year":"1994","team":"Cosenza Nuoto asd","timing":"31.66","score":"788,38"},{"pos":"2","name":"Rendace Piero","year":"1990","team":"asd Anzianotti Nuoto","timing":"42.18","score":"591,75"}]},{"title":"50 Dorso - M30","rows":[{"pos":"1","name":"MAZZUCA GIOVANNI","year":"1989","team":"asd Anzianotti Nuoto","timing":"31.80","score":"789,94"},{"pos":"2","name":"Strangis Francesco","year":"1986","team":"Acli Arvalia Nuoto Lamezi","timing":"34.91","score":"719,56"},{"pos":"3","name":"Masala Antonello","year":"1987","team":"Acli Arvalia Nuoto Lamezi","timing":"36.17","score":"694,50"},{"pos":"4","name":"SAFFIOTI FILIPPO","year":"1985","team":"Nettuno Nuoto asd - Palmi","timing":"41.76","score":"601,53"},{"pos":"5","name":"Manna Ernesto","year":"1986","team":"Cosenza Nuoto asd","timing":"55.07","score":"456,15"}]},{"title":"50 Dorso - M35","rows":[{"pos":"1","name":"NAPOLITANO ANTONIO","year":"1984","team":"asd Anzianotti Nuoto","timing":"39.80","score":"656,03"},{"pos":"2","name":"MURACA STEFANO","year":"1983","team":"asd Anzianotti Nuoto","timing":"40.23","score":"649,02"},{"pos":"3","name":"CUNZOLO GIUSEPPE","year":"1983","team":"Nettuno Nuoto asd - Palmi","timing":"40.44","score":"645,65"},{"pos":"4","name":"Granata Vincenzo","year":"1982","team":"asd Anzianotti Nuoto","timing":"01:07.09","score":"389,18"}]},{"title":"50 Dorso - M40","rows":[{"pos":"1","name":"REAL HERNANDEZ JESUS JONATHAN","year":"1979","team":"asd Anzianotti Nuoto","timing":"33.19","score":"802,05"},{"pos":"2","name":"VONA GIUSEPPE","year":"1975","team":"HdueO Sport & Animaz. CT","timing":"34.73","score":"766,48"},{"pos":"3","name":"Celso Agatino","year":"1975","team":"Cosenza Nuoto asd","timing":"38.69","score":"688,03"},{"pos":"4","name":"Lorenzano Antonio","year":"1979","team":"Lacinia Nuoto","timing":"42.98","score":"619,36"},{"pos":"5","name":"Baratta Luca","year":"1975","team":"Sport4life ssd","timing":"44.14","score":"603,08"},{"pos":"6","name":"SIGNORETTA MASSIMO","year":"1978","team":"Cosenza Nuoto asd","timing":"47.49","score":"560,54"},{"pos":"7","name":"COSENTINO SALVATORE","year":"1977","team":"Catanzaro Nuoto asd","timing":"01:04.33","score":"413,80"},{"pos":"8","name":"Giordano Alessandro","year":"1976","team":"Sport4life ssd","timing":"01:04.67","score":"411,63"},{"pos":"9","name":"URSINO PATRIZIO","year":"1975","team":"Calabria Swim Race asd","timing":"01:10.65","score":"376,79"}]},{"title":"50 Dorso - M45","rows":[{"pos":"1","name":"Scalzo Enrico Salvatore","year":"1972","team":"asd Anzianotti Nuoto","timing":"31.91","score":"853,34"},{"pos":"2","name":"De Marco Fernando","year":"1970","team":"Sport4life ssd","timing":"42.53","score":"640,25"},{"pos":"3","name":"TORCASIO GIUSEPPE","year":"1971","team":"Acli Arvalia Nuoto Lamezi","timing":"42.91","score":"634,58"},{"pos":"4","name":"GRISAFI PIERGIORGIO","year":"1972","team":"Lacinia Nuoto","timing":"47.41","score":"574,35"},{"pos":"5","name":"FIORENZA ILARIO MASSIMO","year":"1972","team":"Calabria Swim Race asd","timing":"47.95","score":"567,88"},{"pos":"6","name":"VIOLA GIANLUCA","year":"1973","team":"Lacinia Nuoto","timing":"54.28","score":"501,66"},{"pos":"7","name":"Cerchiaro Giuseppe","year":"1974","team":"Sport4life ssd","timing":"58.15","score":"468,27"}]},{"title":"50 Dorso - M50","rows":[{"pos":"1","name":"GARGANO GIANCARLO","year":"1966","team":"asd Anzianotti Nuoto","timing":"48.06","score":"589,06"},{"pos":"2","name":"NOTTI ETTORE","year":"1966","team":"Sport4life ssd","timing":"01:04.31","score":"440,21"}]},{"title":"50 Dorso - M55","rows":[{"pos":"1","name":"AMIDEO FELICE","year":"1962","team":"Lacinia Nuoto","timing":"36.09","score":"806,04"},{"pos":"2","name":"VARZI VINCENZO","year":"1963","team":"Gruppo Atletico Sportivo","timing":"37.85","score":"768,56"},{"pos":"3","name":"MILIZIA FABIO","year":"1964","team":"Lacinia Nuoto","timing":"42.22","score":"689,01"},{"pos":"4","name":"MESSINA NICOLA ANTONIO","year":"1960","team":"Lacinia Nuoto","timing":"45.26","score":"642,73"},{"pos":"5","name":"Valentino Pierpaolo","year":"1964","team":"Acli Arvalia Nuoto Lamezi","timing":"46.38","score":"627,21"},{"pos":"6","name":"Gentile Vincenzo","year":"1961","team":"Sport4life ssd","timing":"47.61","score":"611,01"},{"pos":"7","name":"CAPUTO ANTONIO","year":"1962","team":"Sport4life ssd","timing":"48.88","score":"595,13"}]},{"title":"50 Dorso - M60","rows":[{"pos":"1","name":"POSTERINO DOMENICO","year":"1958","team":"Nettuno Nuoto asd - Palmi","timing":"01:03.60","score":"484,75"},{"pos":"2","name":"CROCEROSSA MARCELLO","year":"1958","team":"asd Anzianotti Nuoto","timing":"01:10.00","score":"440,43"}]},{"title":"50 Dorso - M65","rows":[{"pos":"1","name":"GUIDUCCI MAURIZIO","year":"1953","team":"Catanzaro Nuoto asd","timing":"01:08.14","score":"476,23"}]},{"title":"100 Dorso - M25","rows":[{"pos":"1","name":"Tropeano Egor","year":"1992","team":"asd Anzianotti Nuoto","timing":"01:02.21","score":"876,55"}]},{"title":"100 Dorso - M30","rows":[{"pos":"1","name":"Zicarelli Davide Mario","year":"1987","team":"Cosenza Nuoto asd","timing":"01:04.81","score":"850,64"}]},{"title":"100 Dorso - M35","rows":[{"pos":"1","name":"CINTORINO ANTONINO","year":"1982","team":"Calabria Swim Race asd","timing":"01:33.06","score":"611,76"},{"pos":"2","name":"Granata Vincenzo","year":"1982","team":"asd Anzianotti Nuoto","timing":"02:30.43","score":"378,45"}]},{"title":"100 Dorso - M40","rows":[{"pos":"1","name":"IANNI' ROCCO","year":"1977","team":"Nettuno Nuoto asd - Palmi","timing":"01:22.06","score":"701,32"},{"pos":"2","name":"VARONE GIUSEPPE","year":"1976","team":"Nettuno Nuoto asd - Palmi","timing":"01:33.65","score":"614,52"},{"pos":"3","name":"URSINO PATRIZIO","year":"1975","team":"Calabria Swim Race asd","timing":"01:35.55","score":"602,30"},{"pos":"4","name":"Alitto Gabriele","year":"1978","team":"Sport4life ssd","timing":"02:04.38","score":"462,69"}]},{"title":"100 Dorso - M45","rows":[{"pos":"1","name":"BRUNO GIOVANNI","year":"1971","team":"asd Anzianotti Nuoto","timing":"01:34.68","score":"622,94"},{"pos":"2","name":"GRECO ANGELO","year":"1973","team":"asd Anzianotti Nuoto","timing":"01:38.53","score":"598,60"},{"pos":"3","name":"ARMANO REMIGIO","year":"1970","team":"Sport4life ssd","timing":"01:49.04","score":"540,90"}]},{"title":"100 Dorso - M50","rows":[{"pos":"1","name":"TALARICO FRANCESCO","year":"1966","team":"Catanzaro Nuoto asd","timing":"01:56.89","score":"523,40"}]},{"title":"100 Dorso - M55","rows":[{"pos":"1","name":"Gentile Vincenzo","year":"1961","team":"Sport4life ssd","timing":"01:47.98","score":"589,18"},{"pos":"2","name":"Adamo Gennaro","year":"1960","team":"Lacinia Nuoto","timing":"02:29.19","score":"426,44"}]},{"title":"200 Dorso - M30","rows":[{"pos":"1","name":"Zicarelli Davide Mario","year":"1987","team":"Cosenza Nuoto asd","timing":"02:21.72","score":"859,86"}]},{"title":"200 Dorso - M35","rows":[{"pos":"1","name":"ALLORI MARCO","year":"1981","team":"asd Anzianotti Nuoto","timing":"02:43.15","score":"764,14"}]},{"title":"200 Dorso - M50","rows":[{"pos":"1","name":"RODIO ANTONIO","year":"1968","team":"Lacinia Nuoto","timing":"02:53.83","score":"776,16"}]},{"title":"50 Rana - M25","rows":[{"pos":"1","name":"Cerzoso Gaspare","year":"1994","team":"asd Anzianotti Nuoto","timing":"36.85","score":"751,70"},{"pos":"2","name":"Gentile Antonio","year":"1992","team":"Sport4life ssd","timing":"45.05","score":"614,87"}]},{"title":"50 Rana - M30","rows":[{"pos":"1","name":"DASCOLA GIUSEPPE","year":"1989","team":"asd Anzianotti Nuoto","timing":"35.44","score":"784,14"},{"pos":"2","name":"Caracciolo Aldo","year":"1989","team":"Calabria Swim Race asd","timing":"45.94","score":"604,92"}]},{"title":"50 Rana - M35","rows":[{"pos":"1","name":"Santoro Diego","year":"1980","team":"CN Sub Villa S.Giovanni","timing":"32.94","score":"867,33"},{"pos":"2","name":"TENUTA MATTIA","year":"1984","team":"Sport4life ssd","timing":"39.49","score":"723,47"},{"pos":"3","name":"Aiello Francesco","year":"1984","team":"Sport4life ssd","timing":"42.28","score":"675,73"},{"pos":"4","name":"CIPOLLA GAETANO","year":"1981","team":"Wellnext ssd arl","timing":"44.27","score":"645,36"},{"pos":"5","name":"D'ALESSIO ALFONSO","year":"1981","team":"Calabria Swim Race asd","timing":"53.89","score":"530,15"}]},{"title":"50 Rana - M40","rows":[{"pos":"1","name":"Manna Francesco","year":"1978","team":"Cosenza Nuoto asd","timing":"39.07","score":"740,47"},{"pos":"2","name":"Bisogno Giuseppe","year":"1976","team":"Sport4life ssd","timing":"40.59","score":"712,74"},{"pos":"3","name":"Imbrogno Natalino","year":"1977","team":"asd Anzianotti Nuoto","timing":"40.77","score":"709,59"},{"pos":"4","name":"PERRONE NICOLA","year":"1976","team":"Lacinia Nuoto","timing":"41.68","score":"694,10"},{"pos":"5","name":"Favretto Ivan","year":"1978","team":"Sport4life ssd","timing":"43.77","score":"660,95"},{"pos":"6","name":"Bucarelli Luigi","year":"1977","team":"Cosenza Nuoto asd","timing":"48.35","score":"598,35"},{"pos":"7","name":"Consolo Luca","year":"1976","team":"Cosenza Nuoto asd","timing":"50.67","score":"570,95"}]},{"title":"50 Rana - M45","rows":[{"pos":"1","name":"FALBO GIUSEPPE","year":"1973","team":"Calabria Swim Race asd","timing":"42.03","score":"701,88"},{"pos":"2","name":"SPAGNOLO LUCA","year":"1973","team":"CN Sub Villa S.Giovanni","timing":"48.36","score":"610,01"},{"pos":"3","name":"Zappala Raffaele","year":"1973","team":"Lacinia Nuoto","timing":"53.34","score":"553,06"}]},{"title":"50 Rana - M50","rows":[{"pos":"1","name":"DE BENEDITTIS PIERLUIGI","year":"1969","team":"asd Anzianotti Nuoto","timing":"39.96","score":"766,77"},{"pos":"2","name":"Rosa Rocco","year":"1969","team":"Sport4life ssd","timing":"45.79","score":"669,14"},{"pos":"3","name":"CAPANO GIUSEPPE","year":"1965","team":"CS Il Gabbiano Paola ssd","timing":"59.16","score":"517,92"}]},{"title":"50 Rana - M55","rows":[{"pos":"1","name":"CARUSO GIUSEPPE","year":"1960","team":"CS Il Gabbiano Paola ssd","timing":"47.61","score":"666,88"},{"pos":"2","name":"Mastrangelo Giuseppe","year":"1963","team":"Sport4life ssd","timing":"48.59","score":"653,43"},{"pos":"3","name":"CAPILLO STELLARIO","year":"1961","team":"Catanzaro Nuoto asd","timing":"49.67","score":"639,22"},{"pos":"4","name":"Manfredi Riccardo","year":"1964","team":"Sport4life ssd","timing":"51.31","score":"618,79"}]},{"title":"50 Rana - M60","rows":[{"pos":"1","name":"MIRANTE PATRIZIO","year":"1958","team":"asd Anzianotti Nuoto","timing":"40.78","score":"809,96"}]},{"title":"100 Rana - M25","rows":[{"pos":"1","name":"Tropeano Egor","year":"1992","team":"asd Anzianotti Nuoto","timing":"01:05.85","score":"924,37"},{"pos":"2","name":"FERRAGINA GIACOMO","year":"1991","team":"Gruppo Atletico Sportivo","timing":"01:25.49","score":"712,01"},{"pos":"3","name":"SEVERINO MATTEO","year":"1992","team":"Gruppo Atletico Sportivo","timing":"01:34.75","score":"642,43"}]},{"title":"100 Rana - M30","rows":[{"pos":"1","name":"Bartucci Stefano","year":"1985","team":"asd Anzianotti Nuoto","timing":"01:30.79","score":"672,43"},{"pos":"2","name":"PAGLIARO GIUSEPPE","year":"1989","team":"asd Anzianotti Nuoto","timing":"01:40.16","score":"609,52"}]},{"title":"100 Rana - M35","rows":[{"pos":"1","name":"Santoro Diego","year":"1980","team":"CN Sub Villa S.Giovanni","timing":"01:12.13","score":"864,00"},{"pos":"2","name":"Cosimo Gaetano","year":"1983","team":"Nettuno Nuoto asd - Palmi","timing":"01:31.84","score":"678,57"},{"pos":"3","name":"LUCIA ANDREA","year":"1981","team":"Gruppo Atletico Sportivo","timing":"01:35.13","score":"655,10"},{"pos":"4","name":"Aiello Domenico","year":"1984","team":"Gruppo Atletico Sportivo","timing":"02:04.24","score":"501,61"},{"pos":"5","name":"DENARO FRANCESCO","year":"1981","team":"Calabria Swim Race asd","timing":"02:10.15","score":"478,83"}]},{"title":"100 Rana - M40","rows":[{"pos":"1","name":"PERRONE NICOLA","year":"1976","team":"Lacinia Nuoto","timing":"01:31.12","score":"694,03"},{"pos":"2","name":"VARONE GIUSEPPE","year":"1976","team":"Nettuno Nuoto asd - Palmi","timing":"01:32.17","score":"686,12"},{"pos":"3","name":"BELCASTRO GIOVANNI","year":"1979","team":"Cosenza Nuoto asd","timing":"01:47.22","score":"589,82"}]},{"title":"100 Rana - M45","rows":[{"pos":"1","name":"PRETE CRISTIAN","year":"1971","team":"asd Anzianotti Nuoto","timing":"01:31.34","score":"710,42"},{"pos":"2","name":"COMIS GIUSEPPE","year":"1971","team":"Gruppo Atletico Sportivo","timing":"01:36.84","score":"670,07"},{"pos":"3","name":"ARMANO REMIGIO","year":"1970","team":"Sport4life ssd","timing":"01:37.96","score":"662,41"},{"pos":"4","name":"IUDICA GIUSEPPE","year":"1970","team":"HdueO Sport & Animaz. CT","timing":"01:40.70","score":"644,39"},{"pos":"5","name":"CESARIO VINCENZO","year":"1971","team":"Sport4life ssd","timing":"01:45.68","score":"614,02"},{"pos":"6","name":"FIORITO GIUSEPPE","year":"1970","team":"Gruppo Atletico Sportivo","timing":"01:50.10","score":"589,37"},{"pos":"7","name":"SPAGNOLO LUCA","year":"1973","team":"CN Sub Villa S.Giovanni","timing":"01:50.16","score":"589,05"},{"pos":"8","name":"CAPUANO RUGGERO","year":"1973","team":"Lacinia Nuoto","timing":"02:18.20","score":"469,54"},{"pos":"9","name":"TORCASIO VINCENZO","year":"1971","team":"Acli Arvalia Nuoto Lamezi","timing":"02:51.72","score":"377,88"}]},{"title":"100 Rana - M50","rows":[{"pos":"1","name":"DE BENEDITTIS PIERLUIGI","year":"1969","team":"asd Anzianotti Nuoto","timing":"01:27.41","score":"786,07"}]},{"title":"100 Rana - M55","rows":[{"pos":"1","name":"GUIDI FABRIZIO","year":"1961","team":"Circolo Canottieri Aniene","timing":"01:26.18","score":"818,87"},{"pos":"2","name":"CARUSO GIUSEPPE","year":"1960","team":"CS Il Gabbiano Paola ssd","timing":"01:44.95","score":"672,42"},{"pos":"3","name":"ZIZZA ANTONIO","year":"1963","team":"Lacinia Nuoto","timing":"01:54.66","score":"615,47"},{"pos":"4","name":"Verduci Antonino","year":"1964","team":"Cosenza Nuoto asd","timing":"01:57.03","score":"603,01"}]},{"title":"100 Rana - M60","rows":[{"pos":"1","name":"PECORA BRUNO","year":"1959","team":"CN Sub Villa S.Giovanni","timing":"01:44.07","score":"706,26"}]},{"title":"200 Rana - M30","rows":[{"pos":"1","name":"BONOMO SIGISMONDO","year":"1989","team":"Olympiapalermo asd","timing":"02:53.60","score":"777,07"}]},{"title":"200 Rana - M35","rows":[{"pos":"1","name":"ROMEO ANDREA","year":"1982","team":"Calabria Swim Race asd","timing":"03:52.60","score":"590,84"}]},{"title":"200 Rana - M45","rows":[{"pos":"1","name":"PAONE VINCENZO","year":"1973","team":"Catanzaro Nuoto asd","timing":"03:41.65","score":"650,35"},{"pos":"2","name":"FALBO GIUSEPPE","year":"1973","team":"Calabria Swim Race asd","timing":"03:48.68","score":"630,36"},{"pos":"3","name":"SANTORO GIUSEPPE","year":"1971","team":"CS Il Gabbiano Paola ssd","timing":"04:06.08","score":"585,79"}]},{"title":"200 Rana - M55","rows":[{"pos":"1","name":"GUIDI FABRIZIO","year":"1961","team":"Circolo Canottieri Aniene","timing":"03:10.66","score":"821,99"},{"pos":"2","name":"ROTUNDO GIOVANNI","year":"1964","team":"Calabria Swim Race asd","timing":"03:39.79","score":"713,04"}]},{"title":"200 Rana - M60","rows":[{"pos":"1","name":"PAVIGLIANITI ALFREDO ANTONIO","year":"1959","team":"CS Il Gabbiano Paola ssd","timing":"03:05.47","score":"889,74"}]},{"title":"200 Rana - M65","rows":[{"pos":"1","name":"GAROFALO FRANCESCO","year":"1954","team":"Lacinia Nuoto","timing":"03:24.67","score":"855,43"}]},{"title":"50 Farfalla - M25","rows":[{"pos":"1","name":"Preiti Francesco","year":"1993","team":"Cosenza Nuoto asd","timing":"39.29","score":"607,02"}]},{"title":"50 Farfalla - M30","rows":[{"pos":"1","name":"Zicarelli Sergio Luca","year":"1987","team":"Cosenza Nuoto asd","timing":"26.80","score":"904,48"}]},{"title":"50 Farfalla - M35","rows":[{"pos":"1","name":"SORRENTINO PIETRO ANTONIO","year":"1981","team":"Sky Sporting ssd","timing":"32.46","score":"752,93"}]},{"title":"50 Farfalla - M40","rows":[{"pos":"1","name":"MONTIMURRO MASSIMO","year":"1976","team":"asd Anzianotti Nuoto","timing":"29.91","score":"840,19"},{"pos":"2","name":"Argiro' Vitaliano","year":"1977","team":"Calabria Swim Race asd","timing":"37.86","score":"663,76"},{"pos":"3","name":"CASTALDO ARCANGELO","year":"1977","team":"Catanzaro Nuoto asd","timing":"38.16","score":"658,54"},{"pos":"4","name":"MACRI' EMANUELE","year":"1978","team":"asd Anzianotti Nuoto","timing":"38.61","score":"650,87"}]},{"title":"50 Farfalla - M45","rows":[{"pos":"1","name":"BRANCA ALESSANDRO","year":"1971","team":"Sport4life ssd","timing":"37.40","score":"691,44"},{"pos":"2","name":"RUSSO ALESSANDRO","year":"1971","team":"Sport4life ssd","timing":"43.41","score":"595,72"}]},{"title":"50 Farfalla - M50","rows":[{"pos":"1","name":"DI DONNA ANDREA","year":"1967","team":"Cosenza Nuoto asd","timing":"43.39","score":"607,05"},{"pos":"2","name":"LAGANA' DEMETRIO","year":"1968","team":"asd Anzianotti Nuoto","timing":"43.90","score":"600,00"}]},{"title":"50 Farfalla - M55","rows":[{"pos":"1","name":"BOVA PAOLO","year":"1962","team":"Calabria Swim Race asd","timing":"38.62","score":"705,33"},{"pos":"2","name":"CACCURI BAFFA ROSARIO","year":"1961","team":"asd Anzianotti Nuoto","timing":"41.66","score":"653,86"},{"pos":"3","name":"LIBRI DEMETRIO","year":"1962","team":"CN Sub Villa S.Giovanni","timing":"43.87","score":"620,93"},{"pos":"4","name":"SUPPA SALVATORE","year":"1961","team":"Lacinia Nuoto","timing":"55.40","score":"491,70"}]},{"title":"50 Farfalla - M60","rows":[{"pos":"1","name":"GENTILE MARIO","year":"1959","team":"Sport4life ssd","timing":"47.06","score":"602,00"},{"pos":"2","name":"Aloi Giuseppe","year":"1958","team":"Sport4life ssd","timing":"01:04.48","score":"439,36"}]},{"title":"100 Farfalla - M30","rows":[{"pos":"1","name":"Zicarelli Sergio Luca","year":"1987","team":"Cosenza Nuoto asd","timing":"01:00.39","score":"890,21"}]},{"title":"100 Farfalla - M40","rows":[{"pos":"1","name":"VRENNA LUCA","year":"1979","team":"Lacinia Nuoto","timing":"01:10.88","score":"792,47"}]},{"title":"100 Farfalla - M45","rows":[{"pos":"1","name":"FILIPPELLI PAOLO","year":"1973","team":"Lacinia Nuoto","timing":"01:31.46","score":"632,19"}]},{"title":"100 Farfalla - M60","rows":[{"pos":"1","name":"MORABITO GIUSEPPE","year":"1956","team":"CN Sub Villa S.Giovanni","timing":"01:40.49","score":"643,85"}]},{"title":"100 Misti - M30","rows":[{"pos":"1","name":"DE MARIA GIOVANNI","year":"1989","team":"asd Anzianotti Nuoto","timing":"01:10.51","score":"788,26"},{"pos":"2","name":"Lamberti Luca","year":"1985","team":"Sport4life ssd","timing":"01:30.31","score":"615,44"}]},{"title":"100 Misti - M35","rows":[{"pos":"1","name":"PREZIOSI GIANLUCA","year":"1981","team":"Jolly Nuoto Cl. Benevento","timing":"01:16.18","score":"750,33"}]},{"title":"100 Misti - M40","rows":[{"pos":"1","name":"Bisogno Giuseppe","year":"1976","team":"Sport4life ssd","timing":"01:27.10","score":"669,80"}]},{"title":"100 Misti - M45","rows":[{"pos":"1","name":"BRANCA ALESSANDRO","year":"1971","team":"Sport4life ssd","timing":"01:27.14","score":"690,50"},{"pos":"2","name":"Alfano Salvatore","year":"1970","team":"Sport4life ssd","timing":"01:30.01","score":"668,48"},{"pos":"3","name":"PAONE VINCENZO","year":"1973","team":"Catanzaro Nuoto asd","timing":"01:55.69","score":"520,10"}]},{"title":"100 Misti - M50","rows":[{"pos":"1","name":"CASERTA VITALIANO","year":"1967","team":"Calabria Swim Race asd","timing":"01:21.63","score":"753,28"},{"pos":"2","name":"ARBITRIO CARLO","year":"1966","team":"CN Sub Villa S.Giovanni","timing":"01:31.77","score":"670,04"}]},{"title":"100 Misti - M55","rows":[{"pos":"1","name":"BOVA PAOLO","year":"1962","team":"Calabria Swim Race asd","timing":"01:36.07","score":"664,93"},{"pos":"2","name":"SUPPA SALVATORE","year":"1961","team":"Lacinia Nuoto","timing":"02:10.12","score":"490,93"},{"pos":"3","name":"Adamo Gennaro","year":"1960","team":"Lacinia Nuoto","timing":"02:26.75","score":"435,30"}]},{"title":"200 Misti - M30","rows":[{"pos":"1","name":"DASCOLA GIUSEPPE","year":"1989","team":"asd Anzianotti Nuoto","timing":"02:47.32","score":"730,64"}]},{"title":"200 Misti - M40","rows":[{"pos":"1","name":"REAL HERNANDEZ JESUS JONATHAN","year":"1979","team":"asd Anzianotti Nuoto","timing":"02:40.85","score":"796,08"},{"pos":"2","name":"CATONA SIMONE","year":"1978","team":"CN Sub Villa S.Giovanni","timing":"02:55.21","score":"730,84"},{"pos":"3","name":"BORELLO PIETRO","year":"1975","team":"Acli Arvalia Nuoto Lamezi","timing":"02:55.68","score":"728,88"},{"pos":"4","name":"Argiro' Vitaliano","year":"1977","team":"Calabria Swim Race asd","timing":"03:38.31","score":"586,55"}]},{"title":"200 Misti - M45","rows":[{"pos":"1","name":"LO SCAVO FRANCESCO","year":"1974","team":"Catanzaro Nuoto asd","timing":"03:14.90","score":"677,42"}]},{"title":"200 Misti - M60","rows":[{"pos":"1","name":"PAVIGLIANITI ALFREDO ANTONIO","year":"1959","team":"CS Il Gabbiano Paola ssd","timing":"02:56.18","score":"846,41"}]},{"title":"400 Misti - M45","rows":[{"pos":"1","name":"SANTORO GIUSEPPE","year":"1971","team":"CS Il Gabbiano Paola ssd","timing":"07:56.56","score":"595,90"}]},{"title":"50 Stile Libero - M25","rows":[{"pos":"1","name":"Sciammarella Marta","year":"1990","team":"Sport4life ssd","timing":"36.12","score":"709,58"},{"pos":"2","name":"SCICCHITANO ANTONELLA","year":"1991","team":"Gruppo Atletico Sportivo","timing":"41.48","score":"617,89"},{"pos":"3","name":"GRECO ANTONELLA FRANCESCA","year":"1994","team":"Sport4life ssd","timing":"58.18","score":"440,53"}]},{"title":"50 Stile Libero - M30","rows":[{"pos":"1","name":"Staine Wanda","year":"1986","team":"asd Anzianotti Nuoto","timing":"32.39","score":"795,62"},{"pos":"2","name":"Melarosa Carmela Valentina","year":"1985","team":"Sicilia Nuoto ssd","timing":"43.01","score":"599,16"},{"pos":"3","name":"TYMPANI AMANDA","year":"1987","team":"Catanzaro Nuoto asd","timing":"49.16","score":"524,21"},{"pos":"4","name":"Pristera' Valentina","year":"1985","team":"Calabria Swim Race asd","timing":"53.87","score":"478,37"}]},{"title":"50 Stile Libero - M35","rows":[{"pos":"1","name":"Riccio Giusi","year":"1983","team":"asd Anzianotti Nuoto","timing":"37.48","score":"696,64"},{"pos":"2","name":"TIANO MORENA","year":"1984","team":"Sport4life ssd","timing":"42.05","score":"620,93"}]},{"title":"50 Stile Libero - M40","rows":[{"pos":"1","name":"PUGLIESE ALESSANDRA","year":"1979","team":"Cosenza Nuoto asd","timing":"36.88","score":"722,61"},{"pos":"2","name":"GELSOMINO MONICA","year":"1979","team":"Cosenza Nuoto asd","timing":"44.30","score":"601,58"},{"pos":"3","name":"ROCCA SABRINA","year":"1975","team":"Calabria Swim Race asd","timing":"50.47","score":"528,04"},{"pos":"4","name":"Bossi Maria","year":"1977","team":"Lacinia Nuoto","timing":"53.11","score":"501,79"},{"pos":"5","name":"Morrone Manuela","year":"1975","team":"Sport4life ssd","timing":"54.19","score":"491,79"},{"pos":"6","name":"Raso Simona","year":"1978","team":"Catanzaro Nuoto asd","timing":"55.34","score":"481,57"}]},{"title":"50 Stile Libero - M45","rows":[{"pos":"1","name":"GUIDO GIULIA","year":"1971","team":"asd Anzianotti Nuoto","timing":"37.11","score":"728,38"},{"pos":"2","name":"Guerra Valeria","year":"1972","team":"Sport4life ssd","timing":"38.47","score":"702,63"},{"pos":"3","name":"SCOTTO FRANCESCA","year":"1971","team":"Lacinia Nuoto","timing":"43.09","score":"627,29"},{"pos":"4","name":"BILOTTA FRANCESCA","year":"1973","team":"asd Anzianotti Nuoto","timing":"44.14","score":"612,37"}]},{"title":"50 Stile Libero - M50","rows":[{"pos":"1","name":"FEDERICO MARIA GRAZIA","year":"1969","team":"CN Sub Villa S.Giovanni","timing":"43.78","score":"632,25"},{"pos":"2","name":"GENTILE LOREDANA","year":"1967","team":"Lacinia Nuoto","timing":"47.62","score":"581,27"},{"pos":"3","name":"LETIZIA DANILA","year":"1968","team":"Calabria Swim Race asd","timing":"51.37","score":"538,84"},{"pos":"4","name":"GIMIGLIANO MARIA","year":"1967","team":"asd Anzianotti Nuoto","timing":"52.06","score":"531,69"},{"pos":"5","name":"Zurlo Stefania","year":"1966","team":"Lacinia Nuoto","timing":"54.69","score":"506,13"},{"pos":"6","name":"FANELLO LUCIA","year":"1969","team":"Acli Arvalia Nuoto Lamezi","timing":"58.52","score":"473,00"}]},{"title":"50 Stile Libero - M55","rows":[{"pos":"1","name":"SALVEMINI FORTUNATA","year":"1964","team":"Lacinia Nuoto","timing":"37.08","score":"774,27"},{"pos":"2","name":"BRANCATI SANTA","year":"1963","team":"CN Sub Villa S.Giovanni","timing":"48.72","score":"589,29"},{"pos":"3","name":"Petrucci Olga","year":"1963","team":"Sport4life ssd","timing":"58.19","score":"493,38"}]},{"title":"50 Stile Libero - M60","rows":[{"pos":"1","name":"RAFFAELLI PRIMETTA","year":"1955","team":"Gruppo Atletico Sportivo","timing":"44.38","score":"682,74"}]},{"title":"100 Stile Libero - M25","rows":[{"pos":"1","name":"POLITO BERNADETTE ANNA","year":"1994","team":"Calabria Swim Race asd","timing":"01:19.00","score":"706,84"}]},{"title":"100 Stile Libero - M30","rows":[{"pos":"1","name":"DE LUCA ANGELA","year":"1985","team":"asd Anzianotti Nuoto","timing":"01:11.17","score":"791,34"},{"pos":"2","name":"Cribari Serena","year":"1988","team":"asd Anzianotti Nuoto","timing":"01:11.57","score":"786,92"},{"pos":"3","name":"ANELLI IOLANDA","year":"1988","team":"asd Anzianotti Nuoto","timing":"01:35.10","score":"592,22"},{"pos":"4","name":"Pristera' Valentina","year":"1985","team":"Calabria Swim Race asd","timing":"02:11.86","score":"427,12"}]},{"title":"100 Stile Libero - M40","rows":[{"pos":"1","name":"FOTI LEONARDA","year":"1977","team":"CN Sub Villa S.Giovanni","timing":"01:26.66","score":"674,47"},{"pos":"2","name":"MALUCCIO MARIA GIUSEPPINA","year":"1977","team":"Cosenza Nuoto asd","timing":"01:48.66","score":"537,92"}]},{"title":"100 Stile Libero - M45","rows":[{"pos":"1","name":"GUIDO GIULIA","year":"1971","team":"asd Anzianotti Nuoto","timing":"01:32.57","score":"643,95"},{"pos":"2","name":"Yaryna Nina","year":"1974","team":"Sport4life ssd","timing":"01:33.41","score":"638,15"},{"pos":"3","name":"SCOTTO FRANCESCA","year":"1971","team":"Lacinia Nuoto","timing":"01:40.09","score":"595,56"},{"pos":"4","name":"CECCARELLI DANIELA","year":"1972","team":"Catanzaro Nuoto asd","timing":"01:42.53","score":"581,39"},{"pos":"5","name":"VERALDI CINZIA","year":"1971","team":"Catanzaro Nuoto asd","timing":"01:54.19","score":"522,02"},{"pos":"6","name":"BRASCA CATERINA","year":"1971","team":"Cosenza Nuoto asd","timing":"02:01.87","score":"489,13"}]},{"title":"100 Stile Libero - M50","rows":[{"pos":"1","name":"GENTILE LOREDANA","year":"1967","team":"Lacinia Nuoto","timing":"01:48.03","score":"568,36"}]},{"title":"100 Stile Libero - M60","rows":[{"pos":"1","name":"ROSSI VINCENZA","year":"1958","team":"asd Anzianotti Nuoto","timing":"01:32.83","score":"728,54"}]},{"title":"200 Stile Libero - M25","rows":[{"pos":"1","name":"Fiamingo Lucia","year":"1993","team":"Cosenza Nuoto asd","timing":"04:08.86","score":"497,59"}]},{"title":"200 Stile Libero - M40","rows":[{"pos":"1","name":"MALUCCIO MARIA GIUSEPPINA","year":"1977","team":"Cosenza Nuoto asd","timing":"04:00.48","score":"531,98"}]},{"title":"200 Stile Libero - M45","rows":[{"pos":"1","name":"CARTISANO NATALIA MICHELA","year":"1973","team":"CN Sub Villa S.Giovanni","timing":"03:06.50","score":"704,18"}]},{"title":"200 Stile Libero - M50","rows":[{"pos":"1","name":"MOSCARA ROSARIA","year":"1968","team":"CN Sub Villa S.Giovanni","timing":"03:33.61","score":"623,19"}]},{"title":"200 Stile Libero - M60","rows":[{"pos":"1","name":"ROTELLA MATILDE ELEONORA","year":"1956","team":"Calabria Swim Race asd","timing":"03:44.85","score":"664,84"}]},{"title":"400 Stile Libero - M40","rows":[{"pos":"1","name":"DE SANTIS LIDIA","year":"1976","team":"Calabria Swim Race asd","timing":"06:44.00","score":"667,33"}]},{"title":"400 Stile Libero - M45","rows":[{"pos":"1","name":"CARTISANO NATALIA MICHELA","year":"1973","team":"CN Sub Villa S.Giovanni","timing":"06:28.62","score":"714,97"},{"pos":"2","name":"CECCARELLI DANIELA","year":"1972","team":"Catanzaro Nuoto asd","timing":"07:30.92","score":"616,18"}]},{"title":"400 Stile Libero - M50","rows":[{"pos":"1","name":"MOSCARA ROSARIA","year":"1968","team":"CN Sub Villa S.Giovanni","timing":"07:25.87","score":"634,40"},{"pos":"2","name":"FATALE BARBARA","year":"1969","team":"Catanzaro Nuoto asd","timing":"08:51.66","score":"532,03"}]},{"title":"400 Stile Libero - M55","rows":[{"pos":"1","name":"Iacoe Maria Luisa","year":"1964","team":"Sport4life ssd","timing":"06:55.75","score":"710,43"}]},{"title":"400 Stile Libero - M60","rows":[{"pos":"1","name":"RAFFAELLI PRIMETTA","year":"1955","team":"Gruppo Atletico Sportivo","timing":"07:10.89","score":"731,63"}]},{"title":"800 Stile Libero - M45","rows":[{"pos":"1","name":"VERALDI CINZIA","year":"1971","team":"Catanzaro Nuoto asd","timing":"18:54.58","score":"505,19"}]},{"title":"800 Stile Libero - M50","rows":[{"pos":"1","name":"TOCCI ELENA","year":"1967","team":"asd Anzianotti Nuoto","timing":"15:05.91","score":"642,51"}]},{"title":"800 Stile Libero - M55","rows":[{"pos":"1","name":"Iacoe Maria Luisa","year":"1964","team":"Sport4life ssd","timing":"14:07.40","score":"721,93"},{"pos":"2","name":"MARCHESE LIDIA","year":"1964","team":"CN Sub Villa S.Giovanni","timing":"14:22.77","score":"709,06"}]},{"title":"800 Stile Libero - M60","rows":[{"pos":"1","name":"ROTELLA MATILDE ELEONORA","year":"1956","team":"Calabria Swim Race asd","timing":"16:07.67","score":"671,84"}]},{"title":"1500 Stile Libero - M55","rows":[{"pos":"1","name":"MARCHESE LIDIA","year":"1964","team":"CN Sub Villa S.Giovanni","timing":"28:21.95","score":"684,88"}]},{"title":"50 Dorso - M25","rows":[{"pos":"1","name":"Mazzei Maria Cristina","year":"1990","team":"Sport4life ssd","timing":"45.07","score":"645,22"},{"pos":"2","name":"SCICCHITANO ANTONELLA","year":"1991","team":"Gruppo Atletico Sportivo","timing":"56.74","score":"512,51"},{"pos":"3","name":"GRECO ANTONELLA FRANCESCA","year":"1994","team":"Sport4life ssd","timing":"01:02.98","score":"461,73"}]},{"title":"50 Dorso - M30","rows":[{"pos":"1","name":"Staine Wanda","year":"1986","team":"asd Anzianotti Nuoto","timing":"37.45","score":"779,97"},{"pos":"2","name":"Turco Valentina","year":"1989","team":"asd Anzianotti Nuoto","timing":"48.52","score":"602,02"},{"pos":"3","name":"TYMPANI AMANDA","year":"1987","team":"Catanzaro Nuoto asd","timing":"01:02.91","score":"464,31"}]},{"title":"50 Dorso - M35","rows":[{"pos":"1","name":"Riccio Giusi","year":"1983","team":"asd Anzianotti Nuoto","timing":"43.88","score":"679,35"},{"pos":"2","name":"TIANO MORENA","year":"1984","team":"Sport4life ssd","timing":"54.49","score":"547,07"}]},{"title":"50 Dorso - M40","rows":[{"pos":"1","name":"PUGLIESE ALESSANDRA","year":"1979","team":"Cosenza Nuoto asd","timing":"42.43","score":"716,95"},{"pos":"2","name":"Polskaya Iana","year":"1975","team":"Cosenza Nuoto asd","timing":"45.15","score":"673,75"},{"pos":"3","name":"MUSCOLO PATRIZIA","year":"1975","team":"Catanzaro Nuoto asd","timing":"47.12","score":"645,59"}]},{"title":"50 Dorso - M45","rows":[{"pos":"1","name":"BILOTTA FRANCESCA","year":"1973","team":"asd Anzianotti Nuoto","timing":"57.41","score":"540,50"}]},{"title":"50 Dorso - M50","rows":[{"pos":"1","name":"FEDERICO MARIA GRAZIA","year":"1969","team":"CN Sub Villa S.Giovanni","timing":"55.07","score":"585,07"},{"pos":"2","name":"FANELLO LUCIA","year":"1969","team":"Acli Arvalia Nuoto Lamezi","timing":"57.07","score":"564,57"},{"pos":"3","name":"GIMIGLIANO MARIA","year":"1967","team":"asd Anzianotti Nuoto","timing":"01:09.11","score":"466,21"},{"pos":"4","name":"LETIZIA DANILA","year":"1968","team":"Calabria Swim Race asd","timing":"01:10.13","score":"459,43"}]},{"title":"50 Dorso - M55","rows":[{"pos":"1","name":"SALVEMINI FORTUNATA","year":"1964","team":"Lacinia Nuoto","timing":"41.04","score":"827,49"},{"pos":"2","name":"BRANCATI SANTA","year":"1963","team":"CN Sub Villa S.Giovanni","timing":"59.25","score":"573,16"},{"pos":"3","name":"MASTROIANNI SAVERIA","year":"1961","team":"Acli Arvalia Nuoto Lamezi","timing":"01:01.69","score":"550,49"}]},{"title":"100 Dorso - M30","rows":[{"pos":"1","name":"Cribari Serena","year":"1988","team":"asd Anzianotti Nuoto","timing":"01:21.95","score":"772,79"},{"pos":"2","name":"Turco Valentina","year":"1989","team":"asd Anzianotti Nuoto","timing":"01:50.74","score":"571,88"}]},{"title":"100 Dorso - M45","rows":[{"pos":"1","name":"Yaryna Nina","year":"1974","team":"Sport4life ssd","timing":"01:52.47","score":"598,20"}]},{"title":"100 Dorso - M55","rows":[{"pos":"1","name":"MASTROIANNI SAVERIA","year":"1961","team":"Acli Arvalia Nuoto Lamezi","timing":"02:07.48","score":"579,39"}]},{"title":"200 Dorso - M25","rows":[{"pos":"1","name":"Fiamingo Lucia","year":"1993","team":"Cosenza Nuoto asd","timing":"04:43.27","score":"481,73"}]},{"title":"200 Dorso - M35","rows":[{"pos":"1","name":"CATANZARITI LUANA","year":"1980","team":"Calabria Swim Race asd","timing":"04:41.84","score":"495,32"}]},{"title":"50 Rana - M25","rows":[{"pos":"1","name":"Sciammarella Marta","year":"1990","team":"Sport4life ssd","timing":"40.69","score":"784,22"}]},{"title":"50 Rana - M30","rows":[{"pos":"1","name":"BENINCASA SILVIA","year":"1986","team":"Catanzaro Nuoto asd","timing":"55.99","score":"572,96"}]},{"title":"50 Rana - M40","rows":[{"pos":"1","name":"GELSOMINO MONICA","year":"1979","team":"Cosenza Nuoto asd","timing":"53.22","score":"630,59"},{"pos":"2","name":"Giglio Concetta","year":"1978","team":"asd Anzianotti Nuoto","timing":"55.41","score":"605,67"},{"pos":"3","name":"Morrone Manuela","year":"1975","team":"Sport4life ssd","timing":"56.42","score":"594,82"},{"pos":"4","name":"Raso Simona","year":"1978","team":"Catanzaro Nuoto asd","timing":"01:00.91","score":"550,98"}]},{"title":"50 Rana - M45","rows":[{"pos":"1","name":"Guerra Valeria","year":"1972","team":"Sport4life ssd","timing":"49.80","score":"687,75"},{"pos":"2","name":"BRASCA CATERINA","year":"1971","team":"Cosenza Nuoto asd","timing":"01:08.00","score":"503,68"}]},{"title":"50 Rana - M50","rows":[{"pos":"1","name":"Zurlo Stefania","year":"1966","team":"Lacinia Nuoto","timing":"01:07.13","score":"530,76"}]},{"title":"50 Rana - M55","rows":[{"pos":"1","name":"SATULLO MARIA PIA","year":"1963","team":"CN Sub Villa S.Giovanni","timing":"50.81","score":"738,44"},{"pos":"2","name":"Petrucci Olga","year":"1963","team":"Sport4life ssd","timing":"01:18.31","score":"479,12"}]},{"title":"100 Rana - M30","rows":[{"pos":"1","name":"GANCI GRETA","year":"1987","team":"Olympiapalermo asd","timing":"01:20.60","score":"872,83"},{"pos":"2","name":"TORCASIO ROSA CLAUDIA","year":"1985","team":"Acli Arvalia Nuoto Lamezi","timing":"01:51.14","score":"632,99"}]},{"title":"100 Rana - M40","rows":[{"pos":"1","name":"FOTI LEONARDA","year":"1977","team":"CN Sub Villa S.Giovanni","timing":"02:01.29","score":"598,32"},{"pos":"2","name":"Giglio Concetta","year":"1978","team":"asd Anzianotti Nuoto","timing":"02:01.66","score":"596,50"}]},{"title":"100 Rana - M55","rows":[{"pos":"1","name":"SATULLO MARIA PIA","year":"1963","team":"CN Sub Villa S.Giovanni","timing":"01:49.70","score":"754,42"}]},{"title":"200 Rana - M30","rows":[{"pos":"1","name":"GANCI GRETA","year":"1987","team":"Olympiapalermo asd","timing":"02:46.97","score":"927,17"},{"pos":"2","name":"TORCASIO ROSA CLAUDIA","year":"1985","team":"Acli Arvalia Nuoto Lamezi","timing":"04:00.32","score":"644,18"}]},{"title":"200 Rana - M35","rows":[{"pos":"1","name":"CATANZARITI LUANA","year":"1980","team":"Calabria Swim Race asd","timing":"04:06.96","score":"640,95"}]},{"title":"50 Farfalla - M30","rows":[{"pos":"1","name":"Medini Laura","year":"1989","team":"Cosenza Nuoto asd","timing":"32.12","score":"862,39"},{"pos":"2","name":"Melarosa Carmela Valentina","year":"1985","team":"Sicilia Nuoto ssd","timing":"53.26","score":"520,09"},{"pos":"3","name":"BENINCASA SILVIA","year":"1986","team":"Catanzaro Nuoto asd","timing":"01:09.52","score":"398,45"}]},{"title":"50 Farfalla - M40","rows":[{"pos":"1","name":"Polskaya Iana","year":"1975","team":"Cosenza Nuoto asd","timing":"41.00","score":"701,46"}]},{"title":"50 Farfalla - M60","rows":[{"pos":"1","name":"ROSSI VINCENZA","year":"1958","team":"asd Anzianotti Nuoto","timing":"47.95","score":"695,10"}]},{"title":"100 Farfalla - M50","rows":[{"pos":"1","name":"FATALE BARBARA","year":"1969","team":"Catanzaro Nuoto asd","timing":"02:32.10","score":"450,62"}]},{"title":"100 Misti - M25","rows":[{"pos":"1","name":"Mazzei Maria Cristina","year":"1990","team":"Sport4life ssd","timing":"01:42.56","score":"625,00"}]},{"title":"100 Misti - M30","rows":[{"pos":"1","name":"Medini Laura","year":"1989","team":"Cosenza Nuoto asd","timing":"01:13.91","score":"865,11"},{"pos":"2","name":"DE LUCA ANGELA","year":"1985","team":"asd Anzianotti Nuoto","timing":"01:25.75","score":"745,66"}]},{"title":"100 Misti - M40","rows":[{"pos":"1","name":"MUSCOLO PATRIZIA","year":"1975","team":"Catanzaro Nuoto asd","timing":"01:48.54","score":"611,11"}]},{"title":"100 Misti - M50","rows":[{"pos":"1","name":"TOCCI ELENA","year":"1967","team":"asd Anzianotti Nuoto","timing":"01:46.75","score":"654,33"}]},{"title":"200 Misti - M40","rows":[{"pos":"1","name":"DE SANTIS LIDIA","year":"1976","team":"Calabria Swim Race asd","timing":"04:14.38","score":"567,73"}]},{"title":"400 Misti - M25","rows":[{"pos":"1","name":"POLITO BERNADETTE ANNA","year":"1994","team":"Calabria Swim Race asd","timing":"07:29.88","score":"659,26"}]}]}