{"name":"Distanze speciali Lazio","meetingURL":"https://www.federnuoto.it/home/master/circuito-supermaster/eventi-circuito-supermaster.html#/risultati/136722:distanze-speciali-lazio.html","manifestURL":"/component/solrconnect/download.html?file=L3Zhci93d3cvZmluX2ZpbGVzL2V2ZW50aS8wMDAwMTM2NzIyLnBkZg==","dateDay1":"09","dateMonth1":"Novembre","dateYear1":"2019","dateDay2":"10","dateMonth2":"Novembre","dateYear2":"2019","organization":"COMITATO REGIONALE LAZIO","venue1":"STADIO DEL NUOTO - CIVITAVECCHIA","address1":"VIALE LAZIO - LOC. SAN GORDIANO, 19 - Civitavecchia (RM)","venue2":"","address2":"","poolLength":"50","timeLimit":"SI","registration":"14/10 - 03/11 23:45","sections":[]}