{"name":"7° Trofeo Mercatino di Bolzano","meetingURL":"https://www.federnuoto.it/home/master/circuito-supermaster/eventi-circuito-supermaster.html#/risultati/136789:7%C2%B0-trofeo-mercatino-di-bolzano.html","manifestURL":"/component/solrconnect/download.html?file=L3Zhci93d3cvZmluX2ZpbGVzL2V2ZW50aS8wMDAwMTM2Nzg5LnBkZg==","dateDay1":"08","dateMonth1":"Dicembre","dateYear1":"2019","dateDay2":"08","dateMonth2":"Dicembre","dateYear2":"2019","organization":"SSV BOZEN - AMATEURSPORTVEREIN","venue1":"PISCINA COPERTA ALBERT PIRCHER BOLZANO","address1":"VIA MASO DELLA PIEVE, 11 - Bolzano/Bozen (BZ)","venue2":"","address2":"","poolLength":"25","timeLimit":"SI","registration":"15/10 - 02/12 23:45","sections":[]}